{
"type": "FeatureCollection",
"name": "CARDI_158",
"crs": { "type": "name", "properties": { "name": "urn:ogc:def:crs:OGC:1.3:CRS84" } },
"features": [
{ "type": "Feature", "properties": { "osm_id": 12044531858, "name": null, "amenity": "bench", "man_made": null, "leisure": null, "playground": null, "memorial": null }, "geometry": { "type": "Point", "coordinates": [ -3.2243366, 51.4914223 ] } },
{ "type": "Feature", "properties": { "osm_id": 12044532113, "name": null, "amenity": "bench", "man_made": null, "leisure": null, "playground": null, "memorial": null }, "geometry": { "type": "Point", "coordinates": [ -3.2240862, 51.4916687 ] } },
{ "type": "Feature", "properties": { "osm_id": 12044532112, "name": null, "amenity": "bench", "man_made": null, "leisure": null, "playground": null, "memorial": null }, "geometry": { "type": "Point", "coordinates": [ -3.2242048, 51.4917426 ] } },
{ "type": "Feature", "properties": { "osm_id": 12044532011, "name": null, "amenity": "bench", "man_made": null, "leisure": null, "playground": null, "memorial": null }, "geometry": { "type": "Point", "coordinates": [ -3.2248593, 51.4919711 ] } },
{ "type": "Feature", "properties": { "osm_id": 12044531903, "name": null, "amenity": null, "man_made": null, "leisure": "picnic_table", "playground": null, "memorial": null }, "geometry": { "type": "Point", "coordinates": [ -3.2253511, 51.4923318 ] } },
{ "type": "Feature", "properties": { "osm_id": 12044531902, "name": null, "amenity": null, "man_made": null, "leisure": "picnic_table", "playground": null, "memorial": null }, "geometry": { "type": "Point", "coordinates": [ -3.2252633, 51.4924096 ] } },
{ "type": "Feature", "properties": { "osm_id": 12044531905, "name": null, "amenity": null, "man_made": null, "leisure": "picnic_table", "playground": null, "memorial": null }, "geometry": { "type": "Point", "coordinates": [ -3.2251559, 51.4924312 ] } },
{ "type": "Feature", "properties": { "osm_id": 12044531904, "name": null, "amenity": null, "man_made": null, "leisure": "picnic_table", "playground": null, "memorial": null }, "geometry": { "type": "Point", "coordinates": [ -3.2251728, 51.4924848 ] } },
{ "type": "Feature", "properties": { "osm_id": 12044531908, "name": null, "amenity": null, "man_made": null, "leisure": "picnic_table", "playground": null, "memorial": null }, "geometry": { "type": "Point", "coordinates": [ -3.225017, 51.4925108 ] } },
{ "type": "Feature", "properties": { "osm_id": 12044531906, "name": null, "amenity": null, "man_made": null, "leisure": "picnic_table", "playground": null, "memorial": null }, "geometry": { "type": "Point", "coordinates": [ -3.2249838, 51.4925268 ] } },
{ "type": "Feature", "properties": { "osm_id": 12044531907, "name": null, "amenity": null, "man_made": null, "leisure": "picnic_table", "playground": null, "memorial": null }, "geometry": { "type": "Point", "coordinates": [ -3.2250317, 51.492529 ] } },
{ "type": "Feature", "properties": { "osm_id": 12044531886, "name": null, "amenity": null, "man_made": null, "leisure": "picnic_table", "playground": null, "memorial": null }, "geometry": { "type": "Point", "coordinates": [ -3.225148, 51.4925941 ] } },
{ "type": "Feature", "properties": { "osm_id": 12044531883, "name": null, "amenity": null, "man_made": null, "leisure": "picnic_table", "playground": null, "memorial": null }, "geometry": { "type": "Point", "coordinates": [ -3.2250662, 51.4926183 ] } },
{ "type": "Feature", "properties": { "osm_id": 12044531885, "name": null, "amenity": null, "man_made": null, "leisure": "picnic_table", "playground": null, "memorial": null }, "geometry": { "type": "Point", "coordinates": [ -3.2251695, 51.4926371 ] } },
{ "type": "Feature", "properties": { "osm_id": 12044531882, "name": null, "amenity": null, "man_made": null, "leisure": "picnic_table", "playground": null, "memorial": null }, "geometry": { "type": "Point", "coordinates": [ -3.2249234, 51.4926577 ] } },
{ "type": "Feature", "properties": { "osm_id": 12044531884, "name": null, "amenity": null, "man_made": null, "leisure": "picnic_table", "playground": null, "memorial": null }, "geometry": { "type": "Point", "coordinates": [ -3.2250923, 51.4926697 ] } }
]
}
