{
"type": "FeatureCollection",
"name": "VALGL_74_toilets",
"crs": { "type": "name", "properties": { "name": "urn:ogc:def:crs:OGC:1.3:CRS84" } },
"features": [
{ "type": "Feature", "properties": { "name": "Tesco", "payment_info": "Free", "accessible": "Unknown", "radar": "Unknown", "women": "True", "men": "True", "baby_change": "Unknown", "Mon": "Unknown", "Tue": "Unknown", "Wed": "Unknown", "Thu": "Unknown", "Fri": "Unknown", "Sat": "Unknown", "Sun": "Unknown", "index_right": 97, "park_offical_id": "VALGL_74" }, "geometry": { "type": "Point", "coordinates": [ -3.185884953, 51.445722912 ] } },
{ "type": "Feature", "properties": { "name": "Penarth town centre ", "payment_info": "Free", "accessible": "Unknown", "radar": "Unknown", "women": "True", "men": "True", "baby_change": "Unknown", "Mon": "Unknown", "Tue": "Unknown", "Wed": "Unknown", "Thu": "Unknown", "Fri": "Unknown", "Sat": "Unknown", "Sun": "Unknown", "index_right": 97, "park_offical_id": "VALGL_74" }, "geometry": { "type": "Point", "coordinates": [ -3.173265124, 51.439062907 ] } }
]
}
