{
"type": "FeatureCollection",
"name": "RHOCY_0_toilets",
"crs": { "type": "name", "properties": { "name": "urn:ogc:def:crs:OGC:1.3:CRS84" } },
"features": [
{ "type": "Feature", "properties": { "name": "Porth Plaza", "payment_info": "Free", "accessible": "True", "radar": "True", "women": "True", "men": "True", "baby_change": "Unknown", "Mon": "Closed", "Tue": "09:00-18:30", "Wed": "09:00-17:00", "Thu": "09:00-13:00", "Fri": "09:00-18:00", "Sat": "09:00-13:00", "Sun": "Closed", "index_right": 0, "park_offical_id": "RHOCY_0" }, "geometry": { "type": "Point", "coordinates": [ -3.404171169, 51.610431742 ] } },
{ "type": "Feature", "properties": { "name": "Rhondda Heritage Park Museum", "payment_info": "Free", "accessible": "True", "radar": "Unknown", "women": "True", "men": "True", "baby_change": "Unknown", "Mon": "Closed", "Tue": "09:00-16:30", "Wed": "09:00-16:30", "Thu": "09:00-16:30", "Fri": "09:00-16:30", "Sat": "09:00-16:30", "Sun": "Closed", "index_right": 0, "park_offical_id": "RHOCY_0" }, "geometry": { "type": "Point", "coordinates": [ -3.38798672, 51.610581652 ] } },
{ "type": "Feature", "properties": { "name": "Porth town centre", "payment_info": "Cost unknown", "accessible": "True", "radar": "Unknown", "women": "True", "men": "True", "baby_change": "Unknown", "Mon": "Unknown", "Tue": "Unknown", "Wed": "Unknown", "Thu": "Unknown", "Fri": "Unknown", "Sat": "Unknown", "Sun": "Unknown", "index_right": 0, "park_offical_id": "RHOCY_0" }, "geometry": { "type": "Point", "coordinates": [ -3.404890941, 51.610735981 ] } }
]
}
