{
"type": "FeatureCollection",
"name": "RHOCY_35_toilets",
"crs": { "type": "name", "properties": { "name": "urn:ogc:def:crs:OGC:1.3:CRS84" } },
"features": [
{ "type": "Feature", "properties": { "name": "Urinal", "payment_info": "Cost unknown", "accessible": "True", "radar": "False", "women": "False", "men": "True", "baby_change": "False", "Mon": "00:00-00:00", "Tue": "00:00-00:00", "Wed": "00:00-00:00", "Thu": "00:00-00:00", "Fri": "00:00-00:00", "Sat": "00:00-00:00", "Sun": "00:00-00:00", "index_right": 37, "park_offical_id": "RHOCY_35" }, "geometry": { "type": "Point", "coordinates": [ -3.325138089, 51.588391965 ] } },
{ "type": "Feature", "properties": { "name": "Gents Toilet", "payment_info": "Free", "accessible": "False", "radar": "False", "women": "False", "men": "True", "baby_change": "False", "Mon": "00:00-00:00", "Tue": "00:00-00:00", "Wed": "00:00-00:00", "Thu": "00:00-00:00", "Fri": "00:00-00:00", "Sat": "00:00-00:00", "Sun": "00:00-00:00", "index_right": 37, "park_offical_id": "RHOCY_35" }, "geometry": { "type": "Point", "coordinates": [ -3.331775666, 51.597601927 ] } }
]
}
