{
"type": "FeatureCollection",
"name": "CARDI_67_toilets",
"crs": { "type": "name", "properties": { "name": "urn:ogc:def:crs:OGC:1.3:CRS84" } },
"features": [
{ "type": "Feature", "properties": { "name": "Costa Coffee", "payment_info": "Free", "accessible": "Unknown", "radar": "Unknown", "women": "True", "men": "True", "baby_change": "Unknown", "Mon": "Unknown", "Tue": "Unknown", "Wed": "Unknown", "Thu": "Unknown", "Fri": "Unknown", "Sat": "Unknown", "Sun": "Unknown", "index_right": 231, "park_offical_id": "CARDI_67" }, "geometry": { "type": "Point", "coordinates": [ -3.144482374, 51.492997057 ] } },
{ "type": "Feature", "properties": { "name": "Tesco Pengam Green", "payment_info": "Free", "accessible": "Unknown", "radar": "Unknown", "women": "True", "men": "True", "baby_change": "True", "Mon": "06:00-00:00", "Tue": "06:00-00:00", "Wed": "06:00-00:00", "Thu": "06:00-00:00", "Fri": "06:00-00:00", "Sat": "06:00-22:00", "Sun": "10:00-16:00", "index_right": 231, "park_offical_id": "CARDI_67" }, "geometry": { "type": "Point", "coordinates": [ -3.128009, 51.487613 ] } }
]
}
