{
"type": "FeatureCollection",
"name": "CARDI_511_toilets",
"crs": { "type": "name", "properties": { "name": "urn:ogc:def:crs:OGC:1.3:CRS84" } },
"features": [
{ "type": "Feature", "properties": { "name": "Cardiff Queen Street Station", "payment_info": "Free", "accessible": "True", "radar": "False", "women": "True", "men": "True", "baby_change": "False", "Mon": "Unknown", "Tue": "Unknown", "Wed": "Unknown", "Thu": "Unknown", "Fri": "Unknown", "Sat": "Unknown", "Sun": "Unknown", "index_right": 200, "park_offical_id": "CARDI_511" }, "geometry": { "type": "Point", "coordinates": [ -3.170204472, 51.48196277 ] } }
]
}
