{
"type": "FeatureCollection",
"name": "CARDI_804_toilets",
"crs": { "type": "name", "properties": { "name": "urn:ogc:def:crs:OGC:1.3:CRS84" } },
"features": [
{ "type": "Feature", "properties": { "name": "The Central Bar Wetherspoons", "payment_info": "Free", "accessible": "True", "radar": "True", "women": "True", "men": "True", "baby_change": "True", "Mon": "08:00-00:00", "Tue": "08:00-00:00", "Wed": "08:00-00:00", "Thu": "08:00-00:00", "Fri": "08:00-00:00", "Sat": "08:00-00:00", "Sun": "08:00-00:00", "index_right": 261, "park_offical_id": "CARDI_804" }, "geometry": { "type": "Point", "coordinates": [ -3.172880193, 51.483337492 ] } },
{ "type": "Feature", "properties": { "name": "Cardiff Queen Street Station", "payment_info": "Free", "accessible": "True", "radar": "False", "women": "True", "men": "True", "baby_change": "False", "Mon": "Unknown", "Tue": "Unknown", "Wed": "Unknown", "Thu": "Unknown", "Fri": "Unknown", "Sat": "Unknown", "Sun": "Unknown", "index_right": 261, "park_offical_id": "CARDI_804" }, "geometry": { "type": "Point", "coordinates": [ -3.170204472, 51.48196277 ] } }
]
}
