{
"type": "FeatureCollection",
"name": "dd3b3f01389c_visibility",
"crs": { "type": "name", "properties": { "name": "urn:ogc:def:crs:OGC:1.3:CRS84" } },
"features": [
{ "type": "Feature", "properties": { "visible_points": 0, "total_points": 46, "visibility_pct": 0.0 }, "geometry": { "type": "Point", "coordinates": [ -3.231790273021169, 51.528319131101519 ] } },
{ "type": "Feature", "properties": { "visible_points": 0, "total_points": 46, "visibility_pct": 0.0 }, "geometry": { "type": "Point", "coordinates": [ -3.231590577724646, 51.528321230191075 ] } },
{ "type": "Feature", "properties": { "visible_points": 0, "total_points": 54, "visibility_pct": 0.0 }, "geometry": { "type": "Point", "coordinates": [ -3.231693336464186, 51.528428052717814 ] } },
{ "type": "Feature", "properties": { "visible_points": 0, "total_points": 53, "visibility_pct": 0.0 }, "geometry": { "type": "Point", "coordinates": [ -3.231493640709059, 51.528430151657631 ] } },
{ "type": "Feature", "properties": { "visible_points": 0, "total_points": 60, "visibility_pct": 0.0 }, "geometry": { "type": "Point", "coordinates": [ -3.231796095662321, 51.528534875137332 ] } },
{ "type": "Feature", "properties": { "visible_points": 1, "total_points": 60, "visibility_pct": 1.6666666666666667 }, "geometry": { "type": "Point", "coordinates": [ -3.231596399471769, 51.528536974266792 ] } },
{ "type": "Feature", "properties": { "visible_points": 0, "total_points": 58, "visibility_pct": 0.0 }, "geometry": { "type": "Point", "coordinates": [ -3.231396703258038, 51.528539073056834 ] } },
{ "type": "Feature", "properties": { "visible_points": 0, "total_points": 63, "visibility_pct": 0.0 }, "geometry": { "type": "Point", "coordinates": [ -3.231699158693079, 51.528643796768691 ] } },
{ "type": "Feature", "properties": { "visible_points": 3, "total_points": 62, "visibility_pct": 4.838709677419355 }, "geometry": { "type": "Point", "coordinates": [ -3.231499462043917, 51.528645895748397 ] } },
{ "type": "Feature", "properties": { "visible_points": 0, "total_points": 59, "visibility_pct": 0.0 }, "geometry": { "type": "Point", "coordinates": [ -3.231299765371576, 51.52864799438867 ] } },
{ "type": "Feature", "properties": { "visible_points": 0, "total_points": 63, "visibility_pct": 0.0 }, "geometry": { "type": "Point", "coordinates": [ -3.231801918372989, 51.528750619163347 ] } },
{ "type": "Feature", "properties": { "visible_points": 3, "total_points": 63, "visibility_pct": 4.7619047619047619 }, "geometry": { "type": "Point", "coordinates": [ -3.231602221288396, 51.528752718332697 ] } },
{ "type": "Feature", "properties": { "visible_points": 0, "total_points": 61, "visibility_pct": 0.0 }, "geometry": { "type": "Point", "coordinates": [ -3.231402524180618, 51.528754817162621 ] } },
{ "type": "Feature", "properties": { "visible_points": 0, "total_points": 60, "visibility_pct": 0.0 }, "geometry": { "type": "Point", "coordinates": [ -3.23170498099148, 51.528859540809734 ] } },
{ "type": "Feature", "properties": { "visible_points": 2, "total_points": 59, "visibility_pct": 3.3898305084745761 }, "geometry": { "type": "Point", "coordinates": [ -3.23150528344827, 51.528861639829344 ] } },
{ "type": "Feature", "properties": { "visible_points": 0, "total_points": 57, "visibility_pct": 0.0 }, "geometry": { "type": "Point", "coordinates": [ -3.231305585881885, 51.528863738509507 ] } },
{ "type": "Feature", "properties": { "visible_points": 0, "total_points": 52, "visibility_pct": 0.0 }, "geometry": { "type": "Point", "coordinates": [ -3.232007439108643, 51.528964263630904 ] } },
{ "type": "Feature", "properties": { "visible_points": 0, "total_points": 55, "visibility_pct": 0.0 }, "geometry": { "type": "Point", "coordinates": [ -3.231807741153172, 51.528966363179549 ] } },
{ "type": "Feature", "properties": { "visible_points": 0, "total_points": 55, "visibility_pct": 0.0 }, "geometry": { "type": "Point", "coordinates": [ -3.231408345172698, 51.528970561258618 ] } },
{ "type": "Feature", "properties": { "visible_points": 0, "total_points": 51, "visibility_pct": 0.0 }, "geometry": { "type": "Point", "coordinates": [ -3.231208647147695, 51.528972659789019 ] } },
{ "type": "Feature", "properties": { "visible_points": 0, "total_points": 44, "visibility_pct": 0.0 }, "geometry": { "type": "Point", "coordinates": [ -3.232110200164386, 51.529071085703812 ] } },
{ "type": "Feature", "properties": { "visible_points": 0, "total_points": 48, "visibility_pct": 0.0 }, "geometry": { "type": "Point", "coordinates": [ -3.231910501773483, 51.529073185442108 ] } },
{ "type": "Feature", "properties": { "visible_points": 0, "total_points": 49, "visibility_pct": 0.0 }, "geometry": { "type": "Point", "coordinates": [ -3.231311406461675, 51.529079482620538 ] } }
]
}
